autograder_utils/Decorators.py
autograder_utils/JSONTestResult.py
autograder_utils/JSONTestRunner.py
autograder_utils/ResultBuilders.py
autograder_utils/ResultFinalizers.py
autograder_utils/__init__.py
autograder_utils/utils.py
hybridjsontestrunner-1.0.0.dist-info/licenses/LICENSE
hybridjsontestrunner-1.0.0.dist-info/METADATA
hybridjsontestrunner-1.0.0.dist-info/WHEEL
hybridjsontestrunner-1.0.0.dist-info/top_level.txt
hybridjsontestrunner-1.0.0.dist-info/RECORD
