Metadata-Version: 2.4
Name: HybridJSONTestRunner
Version: 1.0.0
Summary: A fork of Gradescope's autograder_utils package that adds support for modern features and PrairieLearn
Author-email: Gregory Bell <trihard.studios@outlook.com>
License: MIT License
Project-URL: Repository, https://github.com/gregbell26/HybridJsonTestRunner
Requires-Python: >=3.5
License-File: LICENSE
Dynamic: license-file
